odoo/addons/l10n_th_withholding_tax_multi/README.rst
odoo/addons/l10n_th_withholding_tax_multi/__init__.py
odoo/addons/l10n_th_withholding_tax_multi/__manifest__.py
odoo/addons/l10n_th_withholding_tax_multi/i18n/l10n_th_withholding_tax_multi.pot
odoo/addons/l10n_th_withholding_tax_multi/models/__init__.py
odoo/addons/l10n_th_withholding_tax_multi/models/account_payment.py
odoo/addons/l10n_th_withholding_tax_multi/readme/CONTRIBUTORS.rst
odoo/addons/l10n_th_withholding_tax_multi/readme/DESCRIPTION.rst
odoo/addons/l10n_th_withholding_tax_multi/readme/USAGE.rst
odoo/addons/l10n_th_withholding_tax_multi/static/description/icon.png
odoo/addons/l10n_th_withholding_tax_multi/static/description/index.html
odoo/addons/l10n_th_withholding_tax_multi/tests/__init__.py
odoo/addons/l10n_th_withholding_tax_multi/tests/account_withholding_tax_test.xml
odoo/addons/l10n_th_withholding_tax_multi/tests/test_withholding_tax_multi.py
odoo/addons/l10n_th_withholding_tax_multi/views/account_payment_view.xml
odoo13_addon_l10n_th_withholding_tax_multi-13.0.1.0.1.dist-info/METADATA
odoo13_addon_l10n_th_withholding_tax_multi-13.0.1.0.1.dist-info/WHEEL
odoo13_addon_l10n_th_withholding_tax_multi-13.0.1.0.1.dist-info/top_level.txt
odoo13_addon_l10n_th_withholding_tax_multi-13.0.1.0.1.dist-info/RECORD
