Metadata-Version: 2.1
Name: odoo13-addon-l10n-th-withholding-tax-multi
Version: 13.0.1.0.1
Summary: Thai Localization - Withholding Tax (multi taxes)
Home-page: https://github.com/OCA/l10n-thailand
Author: Ecosoft, Odoo Community Association (OCA)
Author-email: support@odoo-community.org
License: AGPL-3
Platform: UNKNOWN
Classifier: Programming Language :: Python
Classifier: Framework :: Odoo
Classifier: License :: OSI Approved :: GNU Affero General Public License v3
Classifier: Development Status :: 4 - Beta
Requires-Python: >=3.5
Requires-Dist: odoo13-addon-account-payment-multi-deduction
Requires-Dist: odoo13-addon-l10n-th-withholding-tax
Requires-Dist: odoo (<13.1dev,>=13.0a)
